{
  "asset": {
    "version": "1.1"
  },
  "geometricError": 100,
  "root": {
    "transform": [
      1,
      0,
      0,
      0,
      0,
      1,
      0,
      0,
      0,
      0,
      1,
      0,
      4666519.079507138,
      1194495.7909958444,
      4166592.525834901,
      1
    ],
    "boundingVolume": {
      "box": [
        -0.4950532913208008,
        2.1629209518432617,
        -2.9778175354003906,
        32.89530944824219,
        0,
        0,
        0,
        29.413284301757812,
        0,
        0,
        0,
        35.43229293823242
      ]
    },
    "geometricError": 0,
    "refine": "REPLACE",
    "content": {
      "uri": "building.glb"
    }
  }
}